<archimate:ArchimateDiagramModel
    xmlns:xsi="http://www.w3.org/2001/XMLSchema-instance"
    xmlns:archimate="http://www.archimatetool.com/archimate"
    name="CRM behavior_new_1"
    id="id-56515">
  <children
      xsi:type="archimate:DiagramModelArchimateObject"
      id="id-59489"
      targetConnections="id-59490"
      font="1|Arial|10.0|0|COCOA|1|"
      fontColor="#000000"
      lineColor="#000000"
      fillColor="#afffff">
    <bounds
        x="387"
        y="173"
        width="100"
        height="33"/>
    <archimateElement
        xsi:type="archimate:ApplicationService"
        href="ApplicationService_id-58206.xml#id-58206"/>
  </children>
  <children
      xsi:type="archimate:DiagramModelArchimateObject"
      id="id-59498"
      targetConnections="id-59496"
      font="1|Arial|10.0|0|COCOA|1|"
      fontColor="#000000"
      lineColor="#000000"
      fillColor="#afffff">
    <sourceConnections
        xsi:type="archimate:DiagramModelArchimateConnection"
        id="id-59490"
        font="1|Arial|10.0|0|COCOA|1|"
        fontColor="#000000"
        lineColor="#000000"
        source="id-59498"
        target="id-59489">
      <archimateRelationship
          xsi:type="archimate:RealizationRelationship"
          href="RealizationRelationship_id-58205.xml#id-58205"/>
    </sourceConnections>
    <bounds
        x="370"
        y="273"
        width="133"
        height="53"/>
    <archimateElement
        xsi:type="archimate:ApplicationInteraction"
        href="ApplicationInteraction_id-58199.xml#id-58199"/>
  </children>
  <children
      xsi:type="archimate:DiagramModelArchimateObject"
      id="id-59492"
      targetConnections="id-59495 id-59493"
      font="1|Arial|10.0|0|COCOA|1|"
      fontColor="#000000"
      lineColor="#000000"
      fillColor="#afffff">
    <sourceConnections
        xsi:type="archimate:DiagramModelArchimateConnection"
        id="id-59496"
        font="1|Arial|10.0|0|COCOA|1|"
        fontColor="#000000"
        lineColor="#000000"
        source="id-59492"
        target="id-59498">
      <archimateRelationship
          xsi:type="archimate:AssignmentRelationship"
          href="AssignmentRelationship_id-58198.xml#id-58198"/>
    </sourceConnections>
    <bounds
        x="370"
        y="383"
        width="133"
        height="53"/>
    <archimateElement
        xsi:type="archimate:ApplicationCollaboration"
        href="ApplicationCollaboration_id-58140.xml#id-58140"/>
  </children>
  <children
      xsi:type="archimate:DiagramModelArchimateObject"
      id="id-59494"
      targetConnections="id-59491"
      font="1|Arial|10.0|0|COCOA|1|"
      fontColor="#000000"
      lineColor="#000000"
      fillColor="#afffff">
    <sourceConnections
        xsi:type="archimate:DiagramModelArchimateConnection"
        id="id-59495"
        font="1|Arial|10.0|0|COCOA|1|"
        fontColor="#000000"
        lineColor="#000000"
        source="id-59494"
        target="id-59492">
      <archimateRelationship
          xsi:type="archimate:AssociationRelationship"
          href="AssociationRelationship_id-58179.xml#id-58179"/>
    </sourceConnections>
    <bounds
        x="173"
        y="377"
        width="140"
        height="60"/>
    <archimateElement
        xsi:type="archimate:ApplicationComponent"
        href="ApplicationComponent_id-58114.xml#id-58114"/>
  </children>
  <children
      xsi:type="archimate:DiagramModelArchimateObject"
      id="id-59499"
      font="1|Arial|10.0|0|COCOA|1|"
      fontColor="#000000"
      lineColor="#000000"
      fillColor="#afffff">
    <sourceConnections
        xsi:type="archimate:DiagramModelArchimateConnection"
        id="id-59491"
        font="1|Arial|10.0|0|COCOA|1|"
        fontColor="#000000"
        lineColor="#000000"
        source="id-59499"
        target="id-59494">
      <archimateRelationship
          xsi:type="archimate:CompositionRelationship"
          href="CompositionRelationship_id-58209.xml#id-58209"/>
    </sourceConnections>
    <sourceConnections
        xsi:type="archimate:DiagramModelArchimateConnection"
        id="id-59500"
        font="1|Arial|10.0|0|COCOA|1|"
        fontColor="#000000"
        lineColor="#000000"
        source="id-59499"
        target="id-59497">
      <archimateRelationship
          xsi:type="archimate:CompositionRelationship"
          href="CompositionRelationship_id-58210.xml#id-58210"/>
    </sourceConnections>
    <bounds
        x="327"
        y="507"
        width="160"
        height="53"/>
    <archimateElement
        xsi:type="archimate:ApplicationComponent"
        href="ApplicationComponent_id-56757.xml#id-56757"/>
  </children>
  <children
      xsi:type="archimate:DiagramModelArchimateObject"
      id="id-59497"
      targetConnections="id-59500"
      font="1|Arial|10.0|0|COCOA|1|"
      fontColor="#000000"
      lineColor="#000000"
      fillColor="#afffff">
    <sourceConnections
        xsi:type="archimate:DiagramModelArchimateConnection"
        id="id-59493"
        font="1|Arial|10.0|0|COCOA|1|"
        fontColor="#000000"
        lineColor="#000000"
        source="id-59497"
        target="id-59492">
      <archimateRelationship
          xsi:type="archimate:AssociationRelationship"
          href="AssociationRelationship_id-58138.xml#id-58138"/>
    </sourceConnections>
    <bounds
        x="560"
        y="380"
        width="140"
        height="60"/>
    <archimateElement
        xsi:type="archimate:ApplicationComponent"
        href="ApplicationComponent_id-58139.xml#id-58139"/>
  </children>
</archimate:ArchimateDiagramModel>
